iasm/__init__.py
iasm/arch.py
iasm/cmdline.py
iasm/doc.py
iasm/iasm.py
iasm/mem.py
iasm/shell.py
iasm/datasheets/armv8.json
iasm-0.2.0.data/data/LICENSE
iasm-0.2.0.dist-info/LICENSE
iasm-0.2.0.dist-info/METADATA
iasm-0.2.0.dist-info/WHEEL
iasm-0.2.0.dist-info/entry_points.txt
iasm-0.2.0.dist-info/top_level.txt
iasm-0.2.0.dist-info/RECORD
