Metadata-Version: 2.1
Name: iasm
Version: 0.2.0
Summary: Interactive Assembler
Home-page: https://github.com/bad-address/iasm
Author: Di Paola Martin
Author-email: use-github-issues@example.com
License: GNU GPLv3
Keywords: asm,assembler,assembly,x86,arm
Platform: UNKNOWN
Classifier: Development Status :: 3 - Alpha
Classifier: Intended Audience :: Developers
Classifier: Topic :: Software Development :: Assemblers
Classifier: License :: OSI Approved :: GNU General Public License v3 (GPLv3)
Classifier: Programming Language :: Python :: 3.5
Classifier: Programming Language :: Python :: 3.6
Classifier: Programming Language :: Python :: 3.7
Classifier: Programming Language :: Python :: 3.8
Classifier: Programming Language :: Python :: 3.9
Requires-Python: >=3.7
Requires-Dist: Pygments
Requires-Dist: appdirs
Requires-Dist: bitstring
Requires-Dist: capstone
Requires-Dist: keystone-engine
Requires-Dist: prompt-toolkit
Requires-Dist: pypager
Requires-Dist: tabulate
Requires-Dist: unicorn
Requires-Dist: xview
